cssdeadwood/__init__.py
cssdeadwood/app.py
cssdeadwood/css_extract.py
cssdeadwood/dom_match.py
cssdeadwood/utils.py
cssdeadwood/test/__init__.py
cssdeadwood/test/css_extract_test.py
cssdeadwood/test/css_match_test.py
cssdeadwood/test/files/css/css001.css
cssdeadwood/test/files/html/html001.html
cssdeadwood/test/files/python/python001.py
CssDeadwood-0.3.0.dist-info/LICENCE.txt
CssDeadwood-0.3.0.dist-info/METADATA
CssDeadwood-0.3.0.dist-info/WHEEL
CssDeadwood-0.3.0.dist-info/entry_points.txt
CssDeadwood-0.3.0.dist-info/top_level.txt
CssDeadwood-0.3.0.dist-info/RECORD
