Metadata-Version: 2.1
Name: CssDeadwood
Version: 0.3.0
Summary: Tool to search CSS files for unused CSS selectors.
Home-page: https://github.com/soxofaan/CssDeadwood/
Author: Stefaan Lippens
Author-email: soxofaan@gmail.com
License: MIT
Keywords: css deadcode
Platform: UNKNOWN
Classifier: Programming Language :: Python :: 3
Classifier: License :: OSI Approved :: MIT License
Classifier: Operating System :: OS Independent
Classifier: Environment :: Console
License-File: LICENCE.txt
Requires-Dist: lxml (>=3.1.1)
Requires-Dist: cssselect (>=0.8)
